napari_bioformats/__init__.py
napari_bioformats/_core.py
napari_bioformats/_dialogs.py
napari_bioformats/_downloader.py
napari_bioformats/_version.py
napari_bioformats/loci_tools.jar
napari_bioformats/loci_tools_LICENSE
napari_bioformats/_tests/test_pims.py
napari_bioformats-0.2.1.dist-info/LICENSE
napari_bioformats-0.2.1.dist-info/METADATA
napari_bioformats-0.2.1.dist-info/WHEEL
napari_bioformats-0.2.1.dist-info/entry_points.txt
napari_bioformats-0.2.1.dist-info/top_level.txt
napari_bioformats-0.2.1.dist-info/RECORD
