Metadata-Version: 2.1
Name: napari-bioformats
Version: 0.2.1
Summary: Bioformats for napari, using pims
Home-page: https://github.com/tlambert03/napari-bioformats
Author: Talley Lambert
Author-email: talley.lambert@gmail.com
License: GPL-3.0
Project-URL: Bug Tracker, https://github.com/tlambert03/napari-bioformats/issues
Project-URL: Documentation, https://github.com/tlambert03/napari-bioformats#README.md
Project-URL: Source Code, https://github.com/tlambert03/napari-bioformats
Project-URL: User Support, https://github.com/tlambert03/napari-bioformats/issues
Platform: UNKNOWN
Classifier: Development Status :: 4 - Beta
Classifier: Framework :: napari
Classifier: Intended Audience :: Developers
Classifier: License :: OSI Approved :: GNU General Public License v3 (GPLv3)
Classifier: Operating System :: OS Independent
Classifier: Programming Language :: Python
Classifier: Programming Language :: Python :: 3
Classifier: Programming Language :: Python :: 3 :: Only
Classifier: Programming Language :: Python :: 3.7
Classifier: Programming Language :: Python :: 3.8
Classifier: Programming Language :: Python :: 3.9
Classifier: Topic :: Software Development :: Testing
Requires-Python: >=3.7
License-File: LICENSE
Requires-Dist: jpype1
Requires-Dist: napari-plugin-engine (>=0.1.4)
Requires-Dist: numpy
Requires-Dist: ome-types
Requires-Dist: pims
Requires-Dist: requests
Provides-Extra: testing
Requires-Dist: pytest ; extra == 'testing'
Requires-Dist: pytest-cov ; extra == 'testing'
